HISTORY.rst
LICENSE
MANIFEST.in
README.rst
mawac.py
setup.py
mawac.egg-info/PKG-INFO
mawac.egg-info/SOURCES.txt
mawac.egg-info/dependency_links.txt
mawac.egg-info/requires.txt
mawac.egg-info/top_level.txt