Metadata-Version: 1.1
Name: mawac
Version: 0.1
Summary: Writing RESTful API clients.
Home-page: https://github.com/bninja/wac/
Author: wac
Author-email: wac@example.com
License: Copyright (c) 2012 wac.
